README.md
setup.py
Meh.egg-info/PKG-INFO
Meh.egg-info/SOURCES.txt
Meh.egg-info/dependency_links.txt
Meh.egg-info/top_level.txt
meh/__init__.py
tests/__init__.py
tests/data_types.py
tests/tests.py
tests/validate_collections.py